sklearn3.py
sklearn3-0.0.1.dist-info/LICENSE.txt
sklearn3-0.0.1.dist-info/METADATA
sklearn3-0.0.1.dist-info/WHEEL
sklearn3-0.0.1.dist-info/top_level.txt
sklearn3-0.0.1.dist-info/RECORD
